{
  "meta": {
    "experiment": "idm_regate_multirig_symm",
    "date": "2026-07-22T18:17:02Z",
    "device": "cuda",
    "git_hash": "idm-multirig-wt-8194807",
    "ckpt_md5": "b5f07d9e3dd2ca643949bc86832e6585",
    "ckpt_step": 29999,
    "state_dim": 2048,
    "ft_blocks": 4,
    "ft_steps": 1000,
    "enc_lr": 5e-05,
    "head_lr": 0.0003,
    "n_train": 90,
    "pass_rule": "cross speed R2>0.9 AND yaw R2>0.9 AND ADE@2s < 1.5x in-domain heldout ADE@2s"
  },
  "arms": {
    "frozen": {
      "ft_blocks": 0,
      "train_windows": 7905,
      "train_eps": 90,
      "head_params": 2899724,
      "val": {
        "in_rigA_heldout": {
          "n": 3519,
          "r2": {
            "speed": 0.7686266565255501,
            "yaw_rate": 0.8539037187705623,
            "steer": 0.8002654089679678,
            "long_accel": 0.01449250236335331
          },
          "mae": {
            "speed": 2.7721605644824088,
            "yaw_rate": 0.019607621280927478,
            "steer": 0.012313659499211592,
            "long_accel": 0.5402349911734742
          },
          "ade_2s": 4.073786995442045,
          "de_per_horizon": [
            1.4203845940137716,
            2.8109780277796843,
            4.629201544858181,
            7.434583815116545
          ]
        },
        "in_rigB_heldout": {
          "n": 3519,
          "r2": {
            "speed": 0.7035863063735689,
            "yaw_rate": 0.8711848554707198,
            "steer": 0.6468158380878251,
            "long_accel": 0.012928519242064285
          },
          "mae": {
            "speed": 3.2992139382595735,
            "yaw_rate": 0.02556552498570981,
            "steer": 0.03095313504262023,
            "long_accel": 0.6082578458582782
          },
          "ade_2s": 4.681813510822992,
          "de_per_horizon": [
            1.740334568551269,
            3.4255930745038854,
            5.437323857782458,
            8.124002542454356
          ]
        },
        "cross_heldout_comma": {
          "n": 12420,
          "r2": {
            "speed": 0.44014327310545986,
            "yaw_rate": 0.00019066053438632213,
            "steer": 0.38925965234354076,
            "long_accel": -0.12693801729628595
          },
          "mae": {
            "speed": 7.311003669676173,
            "yaw_rate": 0.2643415828699609,
            "steer": 0.011940977260883388,
            "long_accel": 0.4145171321451665
          },
          "ade_2s": 11.319958238949663,
          "de_per_horizon": [
            3.2516860631523614,
            7.437697450278554,
            13.39462176737184,
            21.195827674995904
          ]
        }
      },
      "verdict": {
        "cross_speed_r2": 0.44014327310545986,
        "cross_yaw_r2": 0.00019066053438632213,
        "cross_ade_2s": 11.319958238949663,
        "in_domain_ade_2s": 4.073786995442045,
        "ade_ratio": 2.778731006705798,
        "PASS": false
      }
    },
    "light_ft": {
      "ft_blocks": 4,
      "train_windows": 7905,
      "train_eps": 90,
      "head_params": 2899724,
      "val": {
        "in_rigA_heldout": {
          "n": 3519,
          "r2": {
            "speed": 0.7637181519284681,
            "yaw_rate": 0.8425379207049308,
            "steer": 0.7856406560647501,
            "long_accel": 0.03248940591407268
          },
          "mae": {
            "speed": 2.8290145965799534,
            "yaw_rate": 0.019931750191866198,
            "steer": 0.012792066670072598,
            "long_accel": 0.5304769380015717
          },
          "ade_2s": 4.197161033366252,
          "de_per_horizon": [
            1.5840413590187181,
            2.9086066621456,
            4.83174845686726,
            7.464247655433432
          ]
        },
        "in_rigB_heldout": {
          "n": 3519,
          "r2": {
            "speed": 0.7395166414051795,
            "yaw_rate": 0.8726329445719516,
            "steer": 0.6274784823188637,
            "long_accel": 0.04092482945270992
          },
          "mae": {
            "speed": 3.137197148666217,
            "yaw_rate": 0.025723321636791623,
            "steer": 0.029703341870209503,
            "long_accel": 0.59802321079177
          },
          "ade_2s": 4.590852510741946,
          "de_per_horizon": [
            1.6689548833662278,
            3.2443553810086265,
            5.4015372157092285,
            8.0485625628837
          ]
        },
        "cross_heldout_comma": {
          "n": 12420,
          "r2": {
            "speed": 0.4517798050422356,
            "yaw_rate": 0.00033783587152236283,
            "steer": 0.5277601824858118,
            "long_accel": -0.09716738410823611
          },
          "mae": {
            "speed": 7.250136819324591,
            "yaw_rate": 0.26531361039276513,
            "steer": 0.010554439828364124,
            "long_accel": 0.40676525263943214
          },
          "ade_2s": 11.329354886995876,
          "de_per_horizon": [
            3.1508994477412275,
            7.360883176056761,
            13.733392909173757,
            21.072244015011762
          ]
        }
      },
      "verdict": {
        "cross_speed_r2": 0.4517798050422356,
        "cross_yaw_r2": 0.00033783587152236283,
        "cross_ade_2s": 11.329354886995876,
        "in_domain_ade_2s": 4.197161033366252,
        "ade_ratio": 2.699290019356104,
        "PASS": false
      }
    }
  }
}